vit_keras/__init__.py
vit_keras/imagenet2012.txt
vit_keras/layers.py
vit_keras/utils.py
vit_keras/visualize.py
vit_keras/vit.py
vit_keras-0.2.0.dist-info/METADATA
vit_keras-0.2.0.dist-info/WHEEL
vit_keras-0.2.0.dist-info/licenses/LICENSE
vit_keras-0.2.0.dist-info/RECORD
