Metadata-Version: 2.4
Name: vit-keras
Version: 0.2.0
Summary: Keras implementation of ViT (Vision Transformer)
Author-email: Fausto Morales <fausto@robinbay.com>
License-Expression: Apache-2.0
License-File: LICENSE
Classifier: Operating System :: MacOS
Classifier: Operating System :: Microsoft :: Windows
Classifier: Operating System :: POSIX :: Linux
Classifier: Operating System :: Unix
Classifier: Programming Language :: Python :: 3
Classifier: Programming Language :: Python :: 3 :: Only
Requires-Python: <3.12,>=3.10
Requires-Dist: scipy
Requires-Dist: validators
Provides-Extra: visualization
Requires-Dist: matplotlib; extra == 'visualization'
